[
 {
  "table":"DDTYPES",
  "data":
  [
   {
    "TYPENAME":"Z11",
    "STATE":"A",
    "TYPEKIND":"CLAS"
   }
  ]
 },
 {
  "table":"SEOCLASS",
  "data":
  [
   {
    "CLSNAME":"Z11",
    "CLSTYPE":0,
    "UUID":"TzD4r8PzH9GC5XD7IInjlg==",
    "REMOTE":""
   }
  ]
 },
 {
  "table":"SEOCLASSDF",
  "data":
  [
   {
    "CLSNAME":"Z11",
    "VERSION":1,
    "CATEGORY":0,
    "EXPOSURE":2,
    "STATE":1,
    "RELEASE":0,
    "AUTHOR":"",
    "CREATEDON":"2026-02-16",
    "CHANGEDBY":"",
    "CHANGEDON":"0000-00-00",
    "CHGDANYBY":"",
    "CHGDANYON":"0000-00-00",
    "CLSEMBED":"",
    "CLSABSTRCT":"",
    "CLSFINAL":"X",
    "CLSCCINCL":"X",
    "CLSDEFATT":"",
    "CLSDEFMTD":"",
    "REFCLSNAME":"",
    "FIXPT":"X",
    "VARCL":"",
    "UNICODE":"X",
    "RSTAT":"",
    "CLSBCIMPL":"",
    "R3RELEASE":"757",
    "CLSBCTRANS":"",
    "CLSBCCAT":0,
    "CLSBCNODEL":"",
    "CLSADDON":"",
    "MSG_ID":"",
    "CLSPROXY":"",
    "CLSSHAREDMEMORY":"",
    "WITH_UNIT_TESTS":"X",
    "DURATION_TYPE":"0",
    "RISK_LEVEL":"0",
    "WITHIN_PACKAGE":""
   }
  ]
 },
 {
  "table":"SEOCLASSTX",
  "data":
  [
   {
    "CLSNAME":"Z11",
    "LANGU":"E",
    "DESCRIPT":"11"
   }
  ]
 },
 {
  "table":"TADIR",
  "data":
  [
   {
    "PGMID":"R3TR",
    "OBJECT":"CLAS",
    "OBJ_NAME":"Z11",
    "KORRNUM":"",
    "SRCSYSTEM":"...",
    "AUTHOR":"ROPL062",
    "SRCDEP":"",
    "DEVCLASS":"ZNA1TR-B",
    "GENFLAG":"",
    "EDTFLAG":"",
    "CPROJECT":" S",
    "MASTERLANG":"E",
    "VERSID":"",
    "PAKNOCHECK":"",
    "OBJSTABLTY":"",
    "COMPONENT":"",
    "CRELEASE":"",
    "DELFLAG":"",
    "TRANSLTTXT":"",
    "CREATED_ON":"2026-02-16",
    "CHECK_DATE":"2026-02-16",
    "CHECK_CFG":""
   }
  ]
 },
 {
  "table":"TMDIR",
  "data":
  [
   {
    "CLASSNAME":"Z11",
    "METHODINDX":0,
    "METHODNAME":" ",
    "FLAGS":0
   }
  ]
 },
 {
  "table":"TRDIR",
  "data":
  [
   {
    "NAME":"Z11===========================CCAU",
    "VARCL":"X",
    "DBAPL":"S",
    "DBNA":"D$",
    "SUBC":"I",
    "APPL":"S",
    "FIXPT":"X",
    "LDBNAME":"D$S",
    "UCCHECK":"X"
   },
   {
    "NAME":"Z11===========================CCDEF",
    "VARCL":"X",
    "DBAPL":"S",
    "DBNA":"D$",
    "SUBC":"I",
    "APPL":"S",
    "FIXPT":"X",
    "LDBNAME":"D$S",
    "UCCHECK":"X"
   },
   {
    "NAME":"Z11===========================CCIMP",
    "VARCL":"X",
    "DBAPL":"S",
    "DBNA":"D$",
    "SUBC":"I",
    "APPL":"S",
    "FIXPT":"X",
    "LDBNAME":"D$S",
    "UCCHECK":"X"
   },
   {
    "NAME":"Z11===========================CCMAC",
    "VARCL":"X",
    "DBAPL":"S",
    "DBNA":"D$",
    "SUBC":"I",
    "APPL":"S",
    "FIXPT":"X",
    "LDBNAME":"D$S",
    "UCCHECK":"X"
   },
   {
    "NAME":"Z11===========================CI",
    "VARCL":"X",
    "DBAPL":"S",
    "DBNA":"D$",
    "SUBC":"I",
    "APPL":"S",
    "FIXPT":"X",
    "LDBNAME":"D$S",
    "UCCHECK":"X"
   },
   {
    "NAME":"Z11===========================CO",
    "VARCL":"X",
    "DBAPL":"S",
    "DBNA":"D$",
    "SUBC":"I",
    "APPL":"S",
    "FIXPT":"X",
    "LDBNAME":"D$S",
    "UCCHECK":"X"
   },
   {
    "NAME":"Z11===========================CP",
    "EDTX":"X",
    "VARCL":"X",
    "DBAPL":"S",
    "DBNA":"D$",
    "SUBC":"K",
    "APPL":"S",
    "FIXPT":"X",
    "LDBNAME":"D$S",
    "UCCHECK":"X"
   },
   {
    "NAME":"Z11===========================CT",
    "DBAPL":"S",
    "DBNA":"D$",
    "SUBC":"I",
    "APPL":"S",
    "FIXPT":"X",
    "LDBNAME":"D$S",
    "UCCHECK":"X"
   },
   {
    "NAME":"Z11===========================CU",
    "VARCL":"X",
    "DBAPL":"S",
    "DBNA":"D$",
    "SUBC":"I",
    "APPL":"S",
    "FIXPT":"X",
    "LDBNAME":"D$S",
    "UCCHECK":"X"
   }
  ]
 }
]